Program_counter/PC.v
module PC(
    input [31:0] PC_input,
    input reset,CLK, // reset,low active
    output reg [31:0] PC_output
);

    always @(posedge CLK) begin
        if(!reset) begin
            PC_output <= 32'b0;
        end 
        else begin 
            PC_output <= PC_input; // "==" like C language is sequential, but "<=" is like doing thing at the same time 
        end 
    end 

endmodule

Program_counter/PC_tb.v
module PC_tb;

    reg [31:0] t_pc_in;
    reg t_res;
    reg t_clk; //In initial and always have to use reg
    wire [31:0] t_pc_out;

    PC uut(
        .PC_input(t_pc_in),
        .CLK(t_clk),
        .reset(t_res),
        .PC_output(t_pc_out)
    );

    initial t_clk = 0; // initial executes once, stargin at simulation time 0,runs sequentially
    // After finishing, the initial block stops forever
    always #5 t_clk = ~t_clk; //always starts at simulation time 0, repeats forever 

    initial begin 
        $dumpfile("pc_wave.vcd");
        $dumpvars(0, PC_tb);
        $monitor("Time=%0t | Reset=%b | In=%d | Out=%d", $time, t_res, t_pc_in, t_pc_out);
        // start test 
        t_res = 0;
        t_pc_in = 32'd100;
        #12
        // set reset to 1 
        t_res = 1;
        #10 // PC read the t_pc_in now 
        //new_input 
        t_pc_in = 32'd200;
        #10
        //new_input 
        t_pc_in = 32'd300;
        #2
        #8
        #20
        $finish;
    end 

endmodule

Program_counter/pc_wave.vcd
$date
	Wed Jan 21 20:34:38 2026
$end
$version
	Icarus Verilog
$end
$timescale
	1s
$end
$scope module PC_tb $end
$var wire 32 ! t_pc_out [31:0] $end
$var reg 1 " t_clk $end
$var reg 32 # t_pc_in [31:0] $end
$var reg 1 $ t_res $end
$scope module uut $end
$var wire 1 " CLK $end
$var wire 32 % PC_input [31:0] $end
$var wire 1 $ reset $end
$var reg 32 & PC_output [31:0] $end
$upscope $end
$upscope $end
$enddefinitions $end
$comment Show the parameter values. $end
$dumpall
$end
#0
$dumpvars
bx &
b1100100 %
0$
b1100100 #
0"
bx !
$end
#5
b0 !
b0 &
1"
#10
0"
#12
1$
#15
b1100100 !
b1100100 &
1"
#20
0"
#22
b11001000 #
b11001000 %
#25
b11001000 !
b11001000 &
1"
#30
0"
#32
b100101100 #
b100101100 %
#35
b100101100 !
b100101100 &
1"
