reg/reg32.v
module reg32(
    input clk,res_n,    //active-low
    input [31:0] in,
    output reg [31:0] out
);

    always @(posedge clk)
    begin 
    if(!res_n)
            out <= 32'b0;
        else 
            out <= in;
    end
endmodule

reg/reg32_tb.v
module reg32_tb;

    reg t_clk;
    reg t_res;
    reg [31:0] t_in;
    wire [31:0] t_out;

    reg32 uut(
        .clk(t_clk),
        .res_n(t_res),
        .in(t_in),
        .out(t_out)
    );

    initial t_clk = 0;
    always #5 t_clk = ~t_clk;

    initial begin 
        $dumpfile("reg32_wave.vcd");
        $dumpvars(0, reg32_tb);
        $monitor("Time=%0t | Reset=%b | In=%d | Out=%d", $time, t_res, t_in, t_out);
        // start test
        t_res = 0;
        t_in = 32'd100;
        #13;
        // unreset 
        t_res = 1;
        #5;
        //new test 
        t_in = 32'd200;
        #10;
        //new
        t_in = 32'd300; 
        #5;

        #20;
        $finish;
    end
     
endmodule

reg/reg32_wave.vcd
$date
	Thu Jan 22 23:07:50 2026
$end
$version
	Icarus Verilog
$end
$timescale
	1s
$end
$scope module reg32_tb $end
$var wire 32 ! t_out [31:0] $end
$var reg 1 " t_clk $end
$var reg 32 # t_in [31:0] $end
$var reg 1 $ t_res $end
$scope module uut $end
$var wire 1 " clk $end
$var wire 32 % in [31:0] $end
$var wire 1 $ res_n $end
$var reg 32 & out [31:0] $end
$upscope $end
$upscope $end
$enddefinitions $end
$comment Show the parameter values. $end
$dumpall
$end
#0
$dumpvars
bx &
b1100100 %
0$
b1100100 #
0"
bx !
$end
#5
b0 !
b0 &
1"
#10
0"
#13
1$
#15
b1100100 !
b1100100 &
1"
#18
b11001000 #
b11001000 %
#20
0"
#25
b11001000 !
b11001000 &
1"
#28
b100101100 #
b100101100 %
#30
0"
#35
b100101100 !
b100101100 &
1"
